Workbook

Sheet About
B8: About
B9: National Aluminium Company Ltd (Nalco) was incorporated in 1981, as a public sector enterprise of the Government of India. It is Asia`s largest integrated aluminium complex, encompassing bauxite mining, alumina refining, aluminium smelting and casting, power generation, rail and port operations. Commissioned during 1985-87, Nalco has emerged to be a star performer in production, export of alumina and aluminium, and more significantly, in propelling a self-sustained growth..The company also in the business activities of Chemicals, Aluminium.
C14: Key Points
C15: Registered Office
C16: Address | D16: Nalco Bhawan,,,Plot No. P/1, Nayapalli,
C17: City | D17: Bhubaneshwar
C18: State | D18: Orissa
C19: Pin Code | D19: 751013
C20: Tel. No. | D20: 0674-2303197
C21: Fax No. | D21: 0674-2300677
C22: Email | D22: company_secretary@nalcoindia.co.in
C23: Internet | D23: http://www.nalcoindia.com
C25: Management - NALCO
C26: Name | D26: Designation
C27: Brijendra Pratap Singh | D27: Chairman & Managing Director
C28: Pankaj Kumar Sharma | D28: Director - Production
C29: Tapas Kumar Pattanayak | D29: Director - Human Resources
C30: Vivek Kumar Bajpai | D30: Part Time Official Director
C31: Patel Sanjaykumar | D31: Part Time Non Official Director
C32: Abhay Kumar Behuria | D32: Director - Finance
C33: Jagdish Arora | D33: Director
C34: Sanjay Lohiya | D34: Part Time Official Director
C35: Trupti Kamlesh Patel | D35: Part Time Non Official Director
C36: Ajay Narang | D36: Part Time Non Official Director

Sheet Promoters
B2: Particulars | C2: 45078 | D2: 45170 | E2: 45261 | F2: 45352 | G2: 45444 | H2: 45536 | I2: 45627 | J2: 45717 | K2: 45809 | L2: 45901 | M2: 45992 | N2: 46082
B3: Promoters - | C3: 0.5128 | D3: 0.5128 | E3: 0.5128 | F3: 0.5128 | G3: 0.5128 | H3: 0.5128 | I3: 0.5128 | J3: 0.5128 | K3: 0.5128 | L3: 0.5128 | M3: 0.5128 | N3: 0.5128
B4: President Of India | C4: 51.28 | D4: 51.28 | E4: 51.28 | F4: 51.28 | G4: 51.28 | H4: 51.28 | I4: 51.28 | J4: 51.28 | K4: 51.28 | L4: 51.28 | M4: 51.28 | N4: 51.28
B5: FIIs - | C5: 0.1495 | D5: 0.1368 | E5: 0.1156 | F5: 0.0899 | G5: 0.1043 | H5: 0.1208 | I5: 0.1413 | J5: 0.1581 | K5: 0.1506 | L5: 0.1622 | M5: 0.1967 | N5: 0.2227
B6: Pinebridge Global Funds - Pinebridge India Equity Fund | I6: 1.01
B7: DIIs - | C7: 0.1538 | D7: 0.1747 | E7: 0.188 | F7: 0.1882 | G7: 0.1912 | H7: 0.1929 | I7: 0.1799 | J7: 0.157 | K7: 0.1576 | L7: 0.1545 | M7: 0.1235 | N7: 0.1075
B8: Lici Gratuity Plus Balanced Fund | C8: 4.28 | D8: 4.19 | E8: 3.29
B9: Icici Prudential Equity Arbitrage Fund | C9: 3.86 | D9: 3.58
B10: Icici Prudential Smallcap Index Fund | F10: 3.25 | G10: 3.34 | H10: 3.68 | I10: 3.67
B11: LIFE INSURANCE CORPORATION OF INDIA - P & GS Fund | F11: 3.29 | G11: 3.51 | H11: 4.22 | I11: 4.02 | J11: 4.02 | K11: 4.02 | L11: 3.7 | M11: 2.6 | N11: 1.94
B12: Bharat 22 ETF | E12: 3.48
B13: Sbi Arbitrage Opportunities Fund | C13: 1.19 | D13: 3.02 | E13: 3.65
B14: Icici Prudential S&P Bse 500 Etf | J14: 2.91 | K14: 3.08 | L14: 2.95 | M14: 2.17 | N14: 1.17
B15: Sbi Psu Fund | F15: 3.57 | G15: 3.62 | H15: 3.64 | I15: 2.21 | J15: 1.84 | K15: 1.71 | L15: 1.62 | M15: 1.39
B16: Quant Mutual Fund-Quant Elss Tax Saver Fund | E16: 1.79 | F16: 2.6 | G16: 2.33
B17: Mirae Asset Large Cap Fund | C17: 2.37 | D17: 2.05 | E17: 2.15
B18: Mirae Asset Nifty Total Market Index Fund | I18: 1.63
B19: Mirae Asset Nifty500 Multicap 50:25:25 Etf | J19: 1.31
B20: Sbi Life Insurance Co. Ltd | M20: 1.06
B21: Public - | C21: 0.184 | D21: 0.1757 | E21: 0.1838 | F21: 0.2093 | G21: 0.1916 | H21: 0.1734 | I21: 0.166 | J21: 0.1721 | K21: 0.179 | L21: 0.1705 | M21: 0.167 | N21: 0.1569
B22: No. of Shareholders | C22: 644039 | D22: 636856 | E22: 692122 | F22: 876645 | G22: 912729 | H22: 868800 | I22: 912049 | J22: 927096 | K22: 956168 | L22: 924942 | M22: 907497 | N22: 969058

Sheet Consolidated FS
B1: Profit & Loss National Aluminium Company Ltd | P1: Balance sheet National Aluminium Company Ltd
B2: Profit & Loss for the year ended 31 march 2025 | J2: % Change | P2: Balance sheet of the year 2025 | X2: % Change
B3: Particulars | C3: 43891 | D3: 44256 | E3: 44621 | F3: 44986 | G3: 45352 | H3: 45717 | J3: 44256 | K3: 44621 | L3: 44986 | M3: 45352 | N3: 45717 | P3: Particulars | Q3: 43891 | R3: 44256 | S3: 44621 | T3: 44986 | U3: 45352 | V3: 45717 | X3: 44256 | Y3: 44621 | Z3: 44986 | AA3: 45352 | AB3: 45717
B4: Sales - | C4: 8472 | D4: 8956 | E4: 14181 | F4: 14257 | G4: 13149 | H4: 16788 | J4: =(D4-C4)/C4 -> 0.057129367 | K4: =(E4-D4)/D4 -> 0.58340777 | L4: =(F4-E4)/E4 -> 0.0053592835 | M4: =(G4-F4)/F4 -> -0.07771621 | N4: =(H4-G4)/G4 -> 0.27675108 | P4: Equity Capital | Q4: 933 | R4: 918 | S4: 918 | T4: 918 | U4: 918 | V4: 918 | X4: =(R4-Q4)/Q4 -> -0.01607717 | Y4: =(S4-R4)/R4 -> 0 | Z4: =(T4-S4)/S4 -> 0 | AA4: =(U4-T4)/T4 -> 0 | AB4: =(V4-U4)/U4 -> 0
B5: Sales Growth % | C5: -0.2633 | D5: 0.0571 | E5: 0.5834 | F5: 0.0054 | G5: -0.0777 | H5: 0.2767 | J5: =(D5-C5)/C5 -> -1.2168629 | K5: =(E5-D5)/D5 -> 9.2171629 | L5: =(F5-E5)/E5 -> -0.99074391 | M5: =(G5-F5)/F5 -> -15.388889 | N5: =(H5-G5)/G5 -> -4.5611326 | P5: Reserves | Q5: 9054 | R5: 9761 | S5: 11634 | T5: 12208 | U5: 13470 | V5: 16887 | X5: =(R5-Q5)/Q5 -> 0.078087033 | Y5: =(S5-R5)/R5 -> 0.19188608 | Z5: =(T5-S5)/S5 -> 0.049338147 | AA5: =(U5-T5)/T5 -> 0.10337484 | AB5: =(V5-U5)/U5 -> 0.25367483
B6: Expenses - | C6: 7985 | D6: 7174 | E6: 9665 | F6: 11917 | G6: 10348 | H6: 9280 | J6: =(D6-C6)/C6 -> -0.10156544 | K6: =(E6-D6)/D6 -> 0.34722609 | L6: =(F6-E6)/E6 -> 0.23300569 | M6: =(G6-F6)/F6 -> -0.13166065 | N6: =(H6-G6)/G6 -> -0.10320835 | P6: Borrowings - | Q6: 12 | R6: 102 | S6: 77 | T6: 105 | U6: 96 | V6: 182 | X6: =(R6-Q6)/Q6 -> 7.5 | Y6: =(S6-R6)/R6 -> -0.24509804 | Z6: =(T6-S6)/S6 -> 0.36363636 | AA6: =(U6-T6)/T6 -> -0.085714286 | AB6: =(V6-U6)/U6 -> 0.89583333
B7: Material Cost % - | C7: 0.1578 | D7: 0.1462 | E7: 0.1308 | F7: 0.2213 | G7: 0.2012 | H7: 0.1175 | J7: =(D7-C7)/C7 -> -0.073510773 | K7: =(E7-D7)/D7 -> -0.10533516 | L7: =(F7-E7)/E7 -> 0.69189602 | M7: =(G7-F7)/F7 -> -0.090826932 | P7: Long term Borrowings | Q7: 9 | R7: 0 | S7: 0 | T7: 0 | U7: 0 | V7: 0
B8: Raw material cost | C8: 1702 | D8: 1315 | E8: 1971 | F8: 3172 | G8: 2792 | H8: 2063 | J8: =(D8-C8)/C8 -> -0.22737955 | K8: =(E8-D8)/D8 -> 0.49885932 | L8: =(F8-E8)/E8 -> 0.60933536 | M8: =(G8-F8)/F8 -> -0.11979823 | P8: Short term Borrowings | Q8: 12 | R8: 46 | S8: 21 | T8: 48 | U8: 39 | V8: 124 | X8: =(R8-Q8)/Q8 -> 2.8333333 | Y8: =(S8-R8)/R8 -> -0.54347826 | Z8: =(T8-S8)/S8 -> 1.2857143 | AA8: =(U8-T8)/T8 -> -0.1875 | AB8: =(V8-U8)/U8 -> 2.1794872
B9: Change in inventory | C9: -365 | D9: -6 | E9: -117 | F9: -17 | G9: -146 | H9: -90 | J9: =(D9-C9)/C9 -> -0.98356164 | K9: =(E9-D9)/D9 -> 18.5 | L9: =(F9-E9)/E9 -> -0.85470085 | M9: =(G9-F9)/F9 -> 7.5882353 | N9: =(H9-G9)/G9 -> -0.38356164 | P9: Lease Liabilities | Q9: 0 | R9: 56 | S9: 56 | T9: 57 | U9: 57 | V9: 58
B10: Manufacturing Cost % | C10: 0.4564 | D10: 0.3931 | E10: 0.3291 | F10: 0.4267 | G10: 0.3736 | H10: 0.2785 | J10: =(D10-C10)/C10 -> -0.13869413 | K10: =(E10-D10)/D10 -> -0.16280845 | L10: =(F10-E10)/E10 -> 0.29656639 | M10: =(G10-F10)/F10 -> -0.1244434 | N10: =(H10-G10)/G10 -> -0.25455032 | P10: Preference Capital | Q10: 0 | R10: 0 | S10: 0 | T10: 0 | U10: 0 | V10: 0
B11: Employee Cost % | C11: 0.2354 | D11: 0.2155 | E11: 0.1661 | F11: 0.1292 | G11: 0.1553 | H11: 0.1071 | J11: =(D11-C11)/C11 -> -0.084536958 | K11: =(E11-D11)/D11 -> -0.22923434 | L11: =(F11-E11)/E11 -> -0.22215533 | M11: =(G11-F11)/F11 -> 0.20201238 | N11: =(H11-G11)/G11 -> -0.31036703 | P11: Other Borrowings | Q11: 0 | R11: 0 | S11: 0 | T11: 0 | U11: 0 | V11: 0
B12: Other Cost % | C12: 0.0929 | D12: 0.0462 | E12: 0.0556 | F12: 0.0587 | G12: 0.0569 | H12: 0.0496 | J12: =(D12-C12)/C12 -> -0.50269107 | K12: =(E12-D12)/D12 -> 0.2034632 | L12: =(F12-E12)/E12 -> 0.055755396 | M12: =(G12-F12)/F12 -> -0.030664395 | N12: =(H12-G12)/G12 -> -0.12829525 | P12: Other Liabilities - | Q12: 4549 | R12: 3928 | S12: 4646 | T12: 4396 | U12: 4751 | V12: 4895 | X12: =(R12-Q12)/Q12 -> -0.13651352 | Y12: =(S12-R12)/R12 -> 0.18279022 | Z12: =(T12-S12)/S12 -> -0.053809729 | AA12: =(U12-T12)/T12 -> 0.080755232 | AB12: =(V12-U12)/U12 -> 0.030309409
B13: Operating Profit | C13: 487 | D13: 1782 | E13: 4516 | F13: 2340 | G13: 2801 | H13: 7508 | J13: =(D13-C13)/C13 -> 2.6591376 | K13: =(E13-D13)/D13 -> 1.5342312 | L13: =(F13-E13)/E13 -> -0.48184234 | M13: =(G13-F13)/F13 -> 0.19700855 | N13: =(H13-G13)/G13 -> 1.6804713 | P13: Trade Payables | Q13: 773 | R13: 940 | S13: 1457 | T13: 1263 | U13: 1496 | V13: 738 | X13: =(R13-Q13)/Q13 -> 0.2160414 | Y13: =(S13-R13)/R13 -> 0.55 | Z13: =(T13-S13)/S13 -> -0.13315031 | AA13: =(U13-T13)/T13 -> 0.18448139 | AB13: =(V13-U13)/U13 -> -0.50668449
B14: OPM % | C14: 0.06 | D14: 0.2 | E14: 0.32 | F14: 0.16 | G14: 0.21 | H14: 0.45 | J14: =(D14-C14)/C14 -> 2.3333333 | K14: =(E14-D14)/D14 -> 0.6 | L14: =(F14-E14)/E14 -> -0.5 | M14: =(G14-F14)/F14 -> 0.3125 | N14: =(H14-G14)/G14 -> 1.1428571 | P14: Advance from Customers | Q14: 0 | R14: 0 | S14: 0 | T14: 0 | U14: 0 | V14: 0
B15: Other Income - | C15: 273 | D15: 147 | E15: 298 | F15: 234 | G15: 678 | H15: 357 | J15: =(D15-C15)/C15 -> -0.46153846 | K15: =(E15-D15)/D15 -> 1.0272109 | L15: =(F15-E15)/E15 -> -0.2147651 | M15: =(G15-F15)/F15 -> 1.8974359 | N15: =(H15-G15)/G15 -> -0.47345133 | P15: Other liability items | Q15: 3776 | R15: 2988 | S15: 3188 | T15: 3132 | U15: 3254 | V15: 4157 | X15: =(R15-Q15)/Q15 -> -0.20868644 | Y15: =(S15-R15)/R15 -> 0.066934404 | Z15: =(T15-S15)/S15 -> -0.017565872 | AA15: =(U15-T15)/T15 -> 0.038952746 | AB15: =(V15-U15)/U15 -> 0.27750461
B16: Exceptional items | C16: 1 | D16: 1 | E16: 0 | F16: 3 | G16: 427 | H16: 1 | J16: =(D16-C16)/C16 -> 0 | K16: =(E16-D16)/D16 -> -1 | M16: =(G16-F16)/F16 -> 141.33333 | P16: Total Liabilities | Q16: 14548 | R16: 14709 | S16: 17276 | T16: 17627 | U16: 19235 | V16: 22882 | X16: =(R16-Q16)/Q16 -> 0.011066813 | Y16: =(S16-R16)/R16 -> 0.174519 | Z16: =(T16-S16)/S16 -> 0.020317203 | AA16: =(U16-T16)/T16 -> 0.091223691 | AB16: =(V16-U16)/U16 -> 0.18960229
B17: Other income normal | C17: 271 | D17: 147 | E17: 297 | F17: 231 | G17: 250 | H17: 356 | J17: =(D17-C17)/C17 -> -0.45756458 | K17: =(E17-D17)/D17 -> 1.0204082 | L17: =(F17-E17)/E17 -> -0.22222222 | M17: =(G17-F17)/F17 -> 0.082251082 | N17: =(H17-G17)/G17 -> 0.424 | P17: Fixed Assets - | Q17: 7485 | R17: 7660 | S17: 7343 | T17: 7303 | U17: 7383 | V17: 7748 | X17: =(R17-Q17)/Q17 -> 0.023380094 | Y17: =(S17-R17)/R17 -> -0.041383812 | Z17: =(T17-S17)/S17 -> -0.0054473648 | AA17: =(U17-T17)/T17 -> 0.010954402 | AB17: =(V17-U17)/U17 -> 0.049437898
B18: Interest | C18: 6 | D18: 7 | E18: 23 | F18: 13 | G18: 17 | H18: 59 | J18: =(D18-C18)/C18 -> 0.16666667 | K18: =(E18-D18)/D18 -> 2.2857143 | L18: =(F18-E18)/E18 -> -0.43478261 | M18: =(G18-F18)/F18 -> 0.30769231 | N18: =(H18-G18)/G18 -> 2.4705882 | P18: Land | Q18: 168 | R18: 267 | S18: 283 | T18: 425 | U18: 797 | V18: 841 | X18: =(R18-Q18)/Q18 -> 0.58928571 | Y18: =(S18-R18)/R18 -> 0.059925094 | Z18: =(T18-S18)/S18 -> 0.50176678 | AA18: =(U18-T18)/T18 -> 0.87529412 | AB18: =(V18-U18)/U18 -> 0.055207026
B19: Depreciation | C19: 530 | D19: 606 | E19: 837 | F19: 716 | G19: 750 | H19: 728 | J19: =(D19-C19)/C19 -> 0.14339623 | K19: =(E19-D19)/D19 -> 0.38118812 | L19: =(F19-E19)/E19 -> -0.14456392 | M19: =(G19-F19)/F19 -> 0.047486034 | N19: =(H19-G19)/G19 -> -0.029333333 | P19: Building | Q19: 756 | R19: 813 | S19: 842 | T19: 863 | U19: 917 | V19: 931 | X19: =(R19-Q19)/Q19 -> 0.075396825 | Y19: =(S19-R19)/R19 -> 0.035670357 | Z19: =(T19-S19)/S19 -> 0.024940618 | AA19: =(U19-T19)/T19 -> 0.062572422 | AB19: =(V19-U19)/U19 -> 0.015267176
B20: Profit before tax | C20: 224 | D20: 1316 | E20: 3954 | F20: 1845 | G20: 2712 | H20: 7078 | J20: =(D20-C20)/C20 -> 4.875 | K20: =(E20-D20)/D20 -> 2.0045593 | L20: =(F20-E20)/E20 -> -0.53338392 | M20: =(G20-F20)/F20 -> 0.4699187 | N20: =(H20-G20)/G20 -> 1.609882 | P20: Plant Machinery | Q20: 8331 | R20: 8808 | S20: 9210 | T20: 9570 | U20: 9924 | V20: 10261 | X20: =(R20-Q20)/Q20 -> 0.057256032 | Y20: =(S20-R20)/R20 -> 0.045640327 | Z20: =(T20-S20)/S20 -> 0.039087948 | AA20: =(U20-T20)/T20 -> 0.036990596 | AB20: =(V20-U20)/U20 -> 0.033958081
B21: Tax % | C21: 0.39 | D21: 0.01 | E21: 0.25 | F21: 0.22 | G21: 0.27 | H21: 0.26 | J21: =(D21-C21)/C21 -> -0.97435897 | K21: =(E21-D21)/D21 -> 24 | L21: =(F21-E21)/E21 -> -0.12 | M21: =(G21-F21)/F21 -> 0.22727273 | N21: =(H21-G21)/G21 -> -0.037037037 | P21: Equipments | Q21: 52 | R21: 52 | S21: 68 | T21: 86 | U21: 99 | V21: 106 | X21: =(R21-Q21)/Q21 -> 0 | Y21: =(S21-R21)/R21 -> 0.30769231 | Z21: =(T21-S21)/S21 -> 0.26470588 | AA21: =(U21-T21)/T21 -> 0.15116279 | AB21: =(V21-U21)/U21 -> 0.070707071
B22: Net Profit - | C22: 136 | D22: 1299 | E22: 2951 | F22: 1435 | G22: 1988 | H22: 5268 | J22: =(D22-C22)/C22 -> 8.5514706 | K22: =(E22-D22)/D22 -> 1.2717475 | L22: =(F22-E22)/E22 -> -0.51372416 | M22: =(G22-F22)/F22 -> 0.38536585 | N22: =(H22-G22)/G22 -> 1.6498994 | P22: Railway sidings | Q22: 64 | R22: 69 | S22: 69 | T22: 85 | U22: 85 | V22: 89 | X22: =(R22-Q22)/Q22 -> 0.078125 | Y22: =(S22-R22)/R22 -> 0 | Z22: =(T22-S22)/S22 -> 0.23188406 | AA22: =(U22-T22)/T22 -> 0 | AB22: =(V22-U22)/U22 -> 0.047058824
B23: Exceptional items AT | C23: 0 | D23: 1 | E23: 0 | F23: 2 | G23: 307 | H23: 0 | P23: Furniture n fittings | Q23: 22 | R23: 24 | S23: 26 | T23: 28 | U23: 29 | V23: 30 | X23: =(R23-Q23)/Q23 -> 0.090909091 | Y23: =(S23-R23)/R23 -> 0.083333333 | Z23: =(T23-S23)/S23 -> 0.076923077 | AA23: =(U23-T23)/T23 -> 0.035714286 | AB23: =(V23-U23)/U23 -> 0.034482759
B24: Exceptional items AT | C24: 0 | D24: 0 | E24: 0 | F24: 0 | G24: 0 | H24: 0 | P24: Vehicles | Q24: 32 | R24: 35 | S24: 39 | T24: 46 | U24: 49 | V24: 51
B25: Profit excl Excep | C25: 136 | D25: 1299 | E25: 2951 | F25: 1433 | G25: 1681 | H25: 5267 | J25: =(D25-C25)/C25 -> 8.5514706 | K25: =(E25-D25)/D25 -> 1.2717475 | L25: =(F25-E25)/E25 -> -0.5144019 | M25: =(G25-F25)/F25 -> 0.1730635 | N25: =(H25-G25)/G25 -> 2.133254 | P25: Intangible Assets | Q25: 90 | R25: 91 | S25: 92 | T25: 92 | U25: 92 | V25: 92 | X25: =(R25-Q25)/Q25 -> 0.011111111 | Y25: =(S25-R25)/R25 -> 0.010989011 | Z25: =(T25-S25)/S25 -> 0 | AA25: =(U25-T25)/T25 -> 0 | AB25: =(V25-U25)/U25 -> 0
B26: Profit for PE | C26: 136 | D26: 1299 | E26: 2951 | F26: 1433 | G26: 1681 | H26: 5267 | J26: =(D26-C26)/C26 -> 8.5514706 | K26: =(E26-D26)/D26 -> 1.2717475 | L26: =(F26-E26)/E26 -> -0.5144019 | M26: =(G26-F26)/F26 -> 0.1730635 | N26: =(H26-G26)/G26 -> 2.133254 | P26: Other fixed assets | Q26: 300 | R26: 391 | S26: 420 | T26: 496 | U26: 505 | V26: 1141 | X26: =(R26-Q26)/Q26 -> 0.30333333 | Y26: =(S26-R26)/R26 -> 0.074168798 | Z26: =(T26-S26)/S26 -> 0.18095238 | AA26: =(U26-T26)/T26 -> 0.018145161 | AB26: =(V26-U26)/U26 -> 1.2594059
B27: Profit for EPS | C27: 136 | D27: 1299 | E27: 2951 | F27: 1435 | G27: 1988 | H27: 5268 | J27: =(D27-C27)/C27 -> 8.5514706 | K27: =(E27-D27)/D27 -> 1.2717475 | L27: =(F27-E27)/E27 -> -0.51372416 | M27: =(G27-F27)/F27 -> 0.38536585 | N27: =(H27-G27)/G27 -> 1.6498994 | P27: Gross Block | Q27: 9816 | R27: 10551 | S27: 11049 | T27: 11692 | U27: 12496 | V27: 13541 | X27: =(R27-Q27)/Q27 -> 0.074877751 | Y27: =(S27-R27)/R27 -> 0.047199318 | Z27: =(T27-S27)/S27 -> 0.058195312 | AA27: =(U27-T27)/T27 -> 0.068764967 | AB27: =(V27-U27)/U27 -> 0.083626761
B28: Profit Growth % | C28: -0.92 | D28: 8.56 | E28: 1.27 | F28: -0.51 | G28: 0.17 | H28: 2.13 | J28: =(D28-C28)/C28 -> -10.304348 | K28: =(E28-D28)/D28 -> -0.85163551 | L28: =(F28-E28)/E28 -> -1.4015748 | M28: =(G28-F28)/F28 -> -1.3333333 | N28: =(H28-G28)/G28 -> 11.529412 | P28: Accumulated Depreciation | Q28: 2331 | R28: 2890 | S28: 3705 | T28: 4389 | U28: 5114 | V28: 5793 | X28: =(R28-Q28)/Q28 -> 0.23981124 | Y28: =(S28-R28)/R28 -> 0.28200692 | Z28: =(T28-S28)/S28 -> 0.18461538 | AA28: =(U28-T28)/T28 -> 0.16518569 | AB28: =(V28-U28)/U28 -> 0.13277278
B29: EPS in Rs | C29: 0.73 | D29: 7.07 | E29: 16.07 | F29: 7.81 | G29: 10.83 | H29: 28.68 | J29: =(D29-C29)/C29 -> 8.6849315 | K29: =(E29-D29)/D29 -> 1.2729844 | L29: =(F29-E29)/E29 -> -0.51400124 | M29: =(G29-F29)/F29 -> 0.38668374 | N29: =(H29-G29)/G29 -> 1.6481994 | P29: CWIP | Q29: 1427 | R29: 1575 | S29: 2235 | T29: 3269 | U29: 4573 | V29: 4936 | X29: =(R29-Q29)/Q29 -> 0.10371409 | Y29: =(S29-R29)/R29 -> 0.41904762 | Z29: =(T29-S29)/S29 -> 0.46263982 | AA29: =(U29-T29)/T29 -> 0.39889875 | AB29: =(V29-U29)/U29 -> 0.079378963
B30: Dividend Payout % | C30: 2.05 | D30: 0.49 | E30: 0.4 | F30: 0.58 | G30: 0.46 | H30: 0.37 | J30: =(D30-C30)/C30 -> -0.76097561 | K30: =(E30-D30)/D30 -> -0.18367347 | L30: =(F30-E30)/E30 -> 0.45 | M30: =(G30-F30)/F30 -> -0.20689655 | N30: =(H30-G30)/G30 -> -0.19565217 | P30: Investments | Q30: 331 | R30: 560 | S30: 375 | T30: 359 | U30: 342 | V30: 774 | X30: =(R30-Q30)/Q30 -> 0.6918429 | Y30: =(S30-R30)/R30 -> -0.33035714 | Z30: =(T30-S30)/S30 -> -0.042666667 | AA30: =(U30-T30)/T30 -> -0.04735376 | AB30: =(V30-U30)/U30 -> 1.2631579
P31: Other Assets - | Q31: 5306 | R31: 4913 | S31: 7322 | T31: 6696 | U31: 6938 | V31: 9424 | X31: =(R31-Q31)/Q31 -> -0.074067094 | Y31: =(S31-R31)/R31 -> 0.49033177 | Z31: =(T31-S31)/S31 -> -0.085495766 | AA31: =(U31-T31)/T31 -> 0.03614098 | AB31: =(V31-U31)/U31 -> 0.35831652
P32: Inventories | Q32: 1697 | R32: 1476 | S32: 1646 | T32: 1840 | U32: 1830 | V32: 1909 | X32: =(R32-Q32)/Q32 -> -0.13022982 | Y32: =(S32-R32)/R32 -> 0.11517615 | Z32: =(T32-S32)/S32 -> 0.11786148 | AA32: =(U32-T32)/T32 -> -0.0054347826 | AB32: =(V32-U32)/U32 -> 0.043169399
P33: Trade receivables - | Q33: 140 | R33: 147 | S33: 75 | T33: 91 | U33: 154 | V33: 186 | X33: =(R33-Q33)/Q33 -> 0.05 | Y33: =(S33-R33)/R33 -> -0.48979592 | Z33: =(T33-S33)/S33 -> 0.21333333 | AA33: =(U33-T33)/T33 -> 0.69230769 | AB33: =(V33-U33)/U33 -> 0.20779221
P34: Receivables over 6m | Q34: 0 | R34: 32 | S34: 50 | T34: 51 | U34: 38 | V34: 18 | AB34: =(V34-U34)/U34 -> -0.52631579
P35: Receivables under 6m | Q35: 140 | R35: 136 | S35: 46 | T35: 54 | U35: 137 | V35: 169 | X35: =(R35-Q35)/Q35 -> -0.028571429 | Y35: =(S35-R35)/R35 -> -0.66176471 | Z35: =(T35-S35)/S35 -> 0.17391304 | AA35: =(U35-T35)/T35 -> 1.537037 | AB35: =(V35-U35)/U35 -> 0.23357664
P36: Prov for Doubtful | Q36: 0 | R36: -20 | S36: -20 | T36: -14 | U36: -21 | V36: 0 | Y36: =IF(R36=0,0,(S36-R36)/ABS(R36)) -> 0 | Z36: =(T36-S36)/S36 -> -0.3 | AA36: =(U36-T36)/T36 -> 0.5 | AB36: =(V36-U36)/U36 -> -1
P37: Cash Equivalents | Q37: 1981 | R37: 1750 | S37: 3706 | T37: 2118 | U37: 2575 | V37: 5427 | X37: =(R37-Q37)/Q37 -> -0.11660777 | Y37: =(S37-R37)/R37 -> 1.1177143 | Z37: =(T37-S37)/S37 -> -0.42849433 | AA37: =(U37-T37)/T37 -> 0.21576959 | AB37: =(V37-U37)/U37 -> 1.1075728
P38: Loans n Advances | Q38: 310 | R38: 307 | S38: 609 | T38: 732 | U38: 680 | V38: 546 | X38: =(R38-Q38)/Q38 -> -0.0096774194 | Y38: =(S38-R38)/R38 -> 0.98371336 | Z38: =(T38-S38)/S38 -> 0.20197044 | AA38: =(U38-T38)/T38 -> -0.071038251 | AB38: =(V38-U38)/U38 -> -0.19705882
P39: Other asset items | Q39: 1179 | R39: 1233 | S39: 1286 | T39: 1915 | U39: 1699 | V39: 1355 | X39: =(R39-Q39)/Q39 -> 0.045801527 | Y39: =(S39-R39)/R39 -> 0.04298459 | Z39: =(T39-S39)/S39 -> 0.48911353 | AA39: =(U39-T39)/T39 -> -0.11279373 | AB39: =(V39-U39)/U39 -> -0.20247204
P40: Total Assets | Q40: 14548 | R40: 14709 | S40: 17276 | T40: 17627 | U40: 19235 | V40: 22882 | X40: =(R40-Q40)/Q40 -> 0.011066813 | Y40: =(S40-R40)/R40 -> 0.174519 | Z40: =(T40-S40)/S40 -> 0.020317203 | AA40: =(U40-T40)/T40 -> 0.091223691 | AB40: =(V40-U40)/U40 -> 0.18960229

Sheet Beta
A2: National Aluminium Corporation | E2: Nifty | I2: Beta Calculation
A3: Date | B3: Close | C3: Return | E3: Date | F3: Close | G3: Return
A4: 43922 | B4: 28.35 | E4: 43922 | F4: 8253.7998 | I4: Srl. No. | J4: Particular | K4: Value | L4: Formula
A5: 43924 | B5: 28.15 | C5: =(B5-B4)/B4 -> -0.0070546737 | E5: 43924 | F5: 8083.7998 | G5: =(F5-F4)/F4 -> -0.020596574 | I5: 1 | J5: Beta | K5: =SLOPE(C5:C1485,G5:G1485) -> 1.3379164 | L5: =+_xlfn.FORMULATEXT(K5) -> =SLOPE(C5:C1485,G5:G1485)
A6: 43928 | B6: 29.35 | C6: =(B6-B5)/B5 -> 0.042628774 | E6: 43928 | F6: 8792.2002 | G6: =(F6-F5)/F5 -> 0.087632105
A7: 43929 | B7: 29.6 | C7: =(B7-B6)/B6 -> 0.0085178876 | E7: 43929 | F7: 8748.75 | G7: =(F7-F6)/F6 -> -0.0049419024 | I7: 2 | J7: Beta | K7: =_xlfn.COVARIANCE.S(C5:C1485,G5:G1485)/_xlfn.VAR.S(G5:G1485) -> 1.3379164 | L7: =+_xlfn.FORMULATEXT(K7) -> =COVARIANCE.S(C5:C1485,G5:G1485)/VAR.S(G5:G1485)
A8: 43930 | B8: 30.4 | C8: =(B8-B7)/B7 -> 0.027027027 | E8: 43930 | F8: 9111.9004 | G8: =(F8-F7)/F7 -> 0.041508832
A9: 43934 | B9: 30.3 | C9: =(B9-B8)/B8 -> -0.0032894737 | E9: 43934 | F9: 8993.8496 | G9: =(F9-F8)/F8 -> -0.012955671 | I9: 3 | J9: SUMMARY OUTPUT
A10: 43936 | B10: 30.25 | C10: =(B10-B9)/B9 -> -0.001650165 | E10: 43936 | F10: 8925.2998 | G10: =(F10-F9)/F9 -> -0.0076218536 | J10: Regression Statistics
A11: 43937 | B11: 31.05 | C11: =(B11-B10)/B10 -> 0.026446281 | E11: 43937 | F11: 8992.7998 | G11: =(F11-F10)/F10 -> 0.0075627712 | J11: Multiple R | K11: 0.47064477
A12: 43938 | B12: 31.95 | C12: =(B12-B11)/B11 -> 0.028985507 | E12: 43938 | F12: 9266.75 | G12: =(F12-F11)/F11 -> 0.030463282 | J12: R Square | K12: 0.2215065
A13: 43941 | B13: 34.1 | C13: =(B13-B12)/B12 -> 0.067292645 | E13: 43941 | F13: 9261.8496 | G13: =(F13-F12)/F12 -> -0.00052881438 | J13: Adjusted R Square | K13: 0.22098013
A14: 43942 | B14: 33.8 | C14: =(B14-B13)/B13 -> -0.008797654 | E14: 43942 | F14: 8981.4502 | G14: =(F14-F13)/F13 -> -0.030274667 | J14: Standard Error | K14: 0.024582704
A15: 43943 | B15: 33.6 | C15: =(B15-B14)/B14 -> -0.0059171598 | E15: 43943 | F15: 9187.2998 | G15: =(F15-F14)/F14 -> 0.022919418 | J15: Observations | K15: 1481
A16: 43944 | B16: 33.7 | C16: =(B16-B15)/B15 -> 0.0029761905 | E16: 43944 | F16: 9313.9004 | G16: =(F16-F15)/F15 -> 0.013779956
A17: 43945 | B17: 31.5 | C17: =(B17-B16)/B16 -> -0.065281899 | E17: 43945 | F17: 9154.4004 | G17: =(F17-F16)/F16 -> -0.017124942 | J17: ANOVA
A18: 43948 | B18: 30.95 | C18: =(B18-B17)/B17 -> -0.017460317 | E18: 43948 | F18: 9282.2998 | G18: =(F18-F17)/F17 -> 0.013971359 | K18: df | L18: SS | M18: MS | N18: F | O18: Significance F
A19: 43949 | B19: 30.5 | C19: =(B19-B18)/B18 -> -0.01453958 | E19: 43949 | F19: 9380.9004 | G19: =(F19-F18)/F18 -> 0.010622431 | J19: Regression | K19: 1 | L19: 0.25430738 | M19: 0.25430738 | N19: 420.82318 | O19: 1.6835724e-82
A20: 43950 | B20: 30.9 | C20: =(B20-B19)/B19 -> 0.013114754 | E20: 43950 | F20: 9553.3496 | G20: =(F20-F19)/F19 -> 0.018383014 | J20: Residual | K20: 1479 | L20: 0.89377353 | M20: 0.00060430935
A21: 43951 | B21: 31.8 | C21: =(B21-B20)/B20 -> 0.029126214 | E21: 43951 | F21: 9859.9004 | G21: =(F21-F20)/F20 -> 0.032088303 | J21: Total | K21: 1480 | L21: 1.1480809
A22: 43955 | B22: 30.2 | C22: =(B22-B21)/B21 -> -0.050314465 | E22: 43955 | F22: 9293.5 | G22: =(F22-F21)/F21 -> -0.057444839
A23: 43956 | B23: 29.15 | C23: =(B23-B22)/B22 -> -0.034768212 | E23: 43956 | F23: 9205.5996 | G23: =(F23-F22)/F22 -> -0.0094582655 | K23: Coefficients | L23: Standard Error | M23: t Stat | N23: P-value | O23: Lower 95% | P23: Upper 95% | Q23: Lower 95.0% | R23: Upper 95.0%
A24: 43957 | B24: 29.1 | C24: =(B24-B23)/B23 -> -0.0017152659 | E24: 43957 | F24: 9270.9004 | G24: =(F24-F23)/F23 -> 0.0070935935 | J24: Intercept | K24: 0.0011895952 | L24: 0.00064050595 | M24: 1.8572743 | N24: 0.063470803 | O24: -6.6801556e-05 | P24: 0.002445992 | Q24: -6.6801556e-05 | R24: 0.002445992
A25: 43958 | B25: 28.85 | C25: =(B25-B24)/B24 -> -0.0085910653 | E25: 43958 | F25: 9199.0498 | G25: =(F25-F24)/F24 -> -0.0077501195 | J25: X Variable 1 | K25: 1.3379164 | L25: 0.065219752 | M25: 20.513975 | N25: 1.6835724e-82 | O25: 1.2099833 | P25: 1.4658494 | Q25: 1.2099833 | R25: 1.4658494
A26: 43959 | B26: 28.35 | C26: =(B26-B25)/B25 -> -0.017331023 | E26: 43959 | F26: 9251.5 | G26: =(F26-F25)/F25 -> 0.0057016971
A27: 43962 | B27: 27.95 | C27: =(B27-B26)/B26 -> -0.014109347 | E27: 43962 | F27: 9239.2002 | G27: =(F27-F26)/F26 -> -0.001329493
A28: 43963 | B28: 27.1 | C28: =(B28-B27)/B27 -> -0.030411449 | E28: 43963 | F28: 9196.5498 | G28: =(F28-F27)/F27 -> -0.0046162427
A29: 43964 | B29: 28.25 | C29: =(B29-B28)/B28 -> 0.042435424 | E29: 43964 | F29: 9383.5498 | G29: =(F29-F28)/F28 -> 0.020333713
A30: 43965 | B30: 28.55 | C30: =(B30-B29)/B29 -> 0.010619469 | E30: 43965 | F30: 9142.75 | G30: =(F30-F29)/F29 -> -0.025661909
A31: 43966 | B31: 28.95 | C31: =(B31-B30)/B30 -> 0.014010508 | E31: 43966 | F31: 9136.8496 | G31: =(F31-F30)/F30 -> -0.00064536279
A32: 43969 | B32: 27.5 | C32: =(B32-B31)/B31 -> -0.050086356 | E32: 43969 | F32: 8823.25 | G32: =(F32-F31)/F31 -> -0.03432251
A33: 43970 | B33: 27.95 | C33: =(B33-B32)/B32 -> 0.016363636 | E33: 43970 | F33: 8879.0996 | G33: =(F33-F32)/F32 -> 0.0063298228
A34: 43971 | B34: 27.9 | C34: =(B34-B33)/B33 -> -0.0017889088 | E34: 43971 | F34: 9066.5498 | G34: =(F34-F33)/F33 -> 0.021111397
A35: 43972 | B35: 28 | C35: =(B35-B34)/B34 -> 0.0035842294 | E35: 43972 | F35: 9106.25 | G35: =(F35-F34)/F34 -> 0.0043787545
A36: 43973 | B36: 26.9 | C36: =(B36-B35)/B35 -> -0.039285714 | E36: 43973 | F36: 9039.25 | G36: =(F36-F35)/F35 -> -0.0073575841
A37: 43977 | B37: 27.65 | C37: =(B37-B36)/B36 -> 0.027881041 | E37: 43977 | F37: 9029.0498 | G37: =(F37-F36)/F36 -> -0.0011284338
... A1485: 46111 | B1485: 386.1 | C1485: =(B1485-B1484)/B1484 -> 0.040700809 | E1485: 46111 | F1485: 22331.4 | G1485: =(F1485-F1484)/F1484 -> -0.021393856

Sheet Assumptions
B2: Particulars | C2: 2021 | D2: 2022 | E2: 2023 | F2: 2024 | G2: 2025
B3: Revenur from Operations | C3: ='Consolidated FS'!D4 -> 8956 | D3: ='Consolidated FS'!E4 -> 14181 | E3: ='Consolidated FS'!F4 -> 14257 | F3: ='Consolidated FS'!G4 -> 13149 | G3: ='Consolidated FS'!H4 -> 16788
B4: Revenue Growth | D4: =(D3-C3)/C3 -> 0.58340777 | E4: =(E3-D3)/D3 -> 0.0053592835 | F4: =(F3-E3)/E3 -> -0.07771621 | G4: =(G3-F3)/F3 -> 0.27675108
B5: Less:Material Cost | C5: ='Consolidated FS'!D6-C6-C7 -> 4830.2148 | D5: ='Consolidated FS'!E6-D6-D7 -> 6521.0723 | E5: ='Consolidated FS'!F6-E6-E7 -> 9238.1097 | F5: ='Consolidated FS'!G6-F6-F7 -> 7557.7822 | G5: ='Consolidated FS'!H6-G6-G7 -> 6649.3204
B6: Less:Employee Cost | C6: ='Consolidated FS'!D11*C3 -> 1930.018 | D6: ='Consolidated FS'!E11*D3 -> 2355.4641 | E6: ='Consolidated FS'!F11*E3 -> 1842.0044 | F6: ='Consolidated FS'!G11*F3 -> 2042.0397 | G6: ='Consolidated FS'!H11*G3 -> 1797.9948
B7: Less: Other Expense | C7: ='Consolidated FS'!D12*C3 -> 413.7672 | D7: ='Consolidated FS'!E12*D3 -> 788.4636 | E7: ='Consolidated FS'!F12*E3 -> 836.8859 | F7: ='Consolidated FS'!G12*F3 -> 748.1781 | G7: ='Consolidated FS'!H12*G3 -> 832.6848
B8: Total Expense | C8: =SUM(C5:C7) -> 7174 | D8: =SUM(D5:D7) -> 9665 | E8: =SUM(E5:E7) -> 11917 | F8: =SUM(F5:F7) -> 10348 | G8: =SUM(G5:G7) -> 9280
B9: EBITDA | C9: =C3-C8 -> 1782 | D9: =D3-D8 -> 4516 | E9: =E3-E8 -> 2340 | F9: =F3-F8 -> 2801 | G9: =G3-G8 -> 7508
B10: Less: Depreciation and Amortization | C10: ='Consolidated FS'!D19 -> 606 | D10: ='Consolidated FS'!E19 -> 837 | E10: ='Consolidated FS'!F19 -> 716 | F10: ='Consolidated FS'!G19 -> 750 | G10: ='Consolidated FS'!H19 -> 728
B11: EBIT | C11: =C9-C10 -> 1176 | D11: =D9-D10 -> 3679 | E11: =E9-E10 -> 1624 | F11: =F9-F10 -> 2051 | G11: =G9-G10 -> 6780
B12: Add: Non Operating Income/Other Income | C12: ='Consolidated FS'!D15 -> 147 | D12: ='Consolidated FS'!E15 -> 298 | E12: ='Consolidated FS'!F15 -> 234 | F12: ='Consolidated FS'!G15 -> 678 | G12: ='Consolidated FS'!H15 -> 357
B13: Less:Interest Expense | C13: ='Consolidated FS'!D18 -> 7 | D13: ='Consolidated FS'!E18 -> 23 | E13: ='Consolidated FS'!F18 -> 13 | F13: ='Consolidated FS'!G18 -> 17 | G13: ='Consolidated FS'!H18 -> 59
B14: EBT | C14: =C11+C12-C13 -> 1316 | D14: =D11+D12-D13 -> 3954 | E14: =E11+E12-E13 -> 1845 | F14: =F11+F12-F13 -> 2712 | G14: =G11+G12-G13 -> 7078
B15: Less: Tax | C15: =C14*'Consolidated FS'!D21 -> 13.16 | D15: =D14*'Consolidated FS'!E21 -> 988.5 | E15: =E14*'Consolidated FS'!F21 -> 405.9 | F15: =F14*'Consolidated FS'!G21 -> 732.24 | G15: =G14*'Consolidated FS'!H21 -> 1840.28
B16: Less:Non Controlling Interest/Minority Interest | D16: 0 | E16: 0 | F16: 0 | G16: 0
B17: PAT | C17: =C14-C15-C16 -> 1302.84 | D17: =D14-D15-D16 -> 2965.5 | E17: =E14-E15-E16 -> 1439.1 | F17: =F14-F15-F16 -> 1979.76 | G17: =G14-G15-G16 -> 5237.72
B19: Historical Growth
B20: Average Growth | C20: =AVERAGE(D4:G4) -> 0.19695048
B21: CAGR | C21: =(G3/C3)^(1/4)-1 -> 0.17009526 | D21: =_xlfn.RRI(4,C3,G3) -> 0.17009526
B22: Margin Analysis
B23: EBITDA Margin | C23: =C9/C3 -> 0.19897276 | D23: =D9/D3 -> 0.31845427 | E23: =E9/E3 -> 0.1641299 | F23: =F9/F3 -> 0.21302 | G23: =G9/G3 -> 0.44722421
B24: EBIT Margin | C24: =C11/C3 -> 0.13130862 | D24: =D11/D3 -> 0.25943163 | E24: =E11/E3 -> 0.11390896 | F24: =F11/F3 -> 0.15598144 | G24: =G11/G3 -> 0.4038599
B25: EBT Margin | C25: =C14/C3 -> 0.1469406 | D25: =D14/D3 -> 0.27882378 | E25: =E14/E3 -> 0.12941011 | F25: =F14/F3 -> 0.20625143 | G25: =G14/G3 -> 0.42161067
B26: PAT Margin | C26: =C17/C3 -> 0.14547119 | D26: =D17/D3 -> 0.20911783 | E26: =E17/E3 -> 0.10093989 | F26: =F17/F3 -> 0.15056354 | G26: =G17/G3 -> 0.3119919
B28: Tax Rate
B29: Effective Tax Rate | C29: =C15/C14 -> 0.01 | D29: =D15/D14 -> 0.25 | E29: =E15/E14 -> 0.22 | F29: =F15/F14 -> 0.27 | G29: =G15/G14 -> 0.26
B30: Marginal Tax Rate | C30: 0.25 | D30: 0.25 | E30: 0.25 | F30: 0.25 | G30: 0.25
B32: Return on Capital
B33: EBIT(1-t) | C33: =C11*(1-C30) -> 882 | D33: =D11*(1-D30) -> 2759.25 | E33: =E11*(1-E30) -> 1218 | F33: =F11*(1-F30) -> 1538.25 | G33: =G11*(1-G30) -> 5085
B34: Book Equity | C34: ='Consolidated FS'!R4+'Consolidated FS'!R5 -> 10679 | D34: ='Consolidated FS'!S4+'Consolidated FS'!S5 -> 12552 | E34: ='Consolidated FS'!T4+'Consolidated FS'!T5 -> 13126 | F34: ='Consolidated FS'!U4+'Consolidated FS'!U5 -> 14388 | G34: ='Consolidated FS'!V4+'Consolidated FS'!V5 -> 17805
B35: Book Debt | C35: ='Consolidated FS'!R6 -> 102 | D35: ='Consolidated FS'!S6 -> 77 | E35: ='Consolidated FS'!T6 -> 105 | F35: ='Consolidated FS'!U6 -> 96 | G35: ='Consolidated FS'!V6 -> 182
B36: Cash and Cash Equivalents | C36: ='Consolidated FS'!R37 -> 1750 | D36: ='Consolidated FS'!S37 -> 3706 | E36: ='Consolidated FS'!T37 -> 2118 | F36: ='Consolidated FS'!U37 -> 2575 | G36: ='Consolidated FS'!V37 -> 5427
B37: Capital Employed | C37: =C34+C35+C36 -> 12531 | D37: =D34+D35+D36 -> 16335 | E37: =E34+E35+E36 -> 15349 | F37: =F34+F35+F36 -> 17059 | G37: =G34+G35+G36 -> 23414
B39: Pre Tax Return on Capital | C39: =C11/C37 -> 0.093847259 | D39: =D11/D37 -> 0.22522192 | E39: =E11/E37 -> 0.10580494 | F39: =F11/F37 -> 0.12022979 | G39: =G11/G37 -> 0.28957034
B40: Post Tax Return on Capital | C40: =C33/C37 -> 0.070385444 | D40: =D33/D37 -> 0.16891644 | E40: =E33/E37 -> 0.079353704 | F40: =F33/F37 -> 0.090172343 | G40: =G33/G37 -> 0.21717776
B42: Growth Summary
B43: Average Revenue Growth | C43: =AVERAGE(D4:G4) -> 0.19695048
B44: Revenue CAGR | C44: =(G3/C3)^(1/4)-1 -> 0.17009526
B46: Growth in EBIT | C46: =FCFF!C13*G40 -> 0.014469381

Sheet Ratios
B2: Ratios
B3: Particulars | C3: 2021 | D3: 2022 | E3: 2023 | F3: 2024 | G3: 2025 | H3: Trend | I3: Mean | J3: Median
B4: Growth Ratios
B5: Sales Growth | D5: =(Assumptions!D3-Assumptions!C3)/ABS(Assumptions!C3) -> 0.58340777 | E5: =(Assumptions!E3-Assumptions!D3)/ABS(Assumptions!D3) -> 0.0053592835 | F5: =(Assumptions!F3-Assumptions!E3)/ABS(Assumptions!E3) -> -0.07771621 | G5: =(Assumptions!G3-Assumptions!F3)/ABS(Assumptions!F3) -> 0.27675108 | I5: =AVERAGE(D5:G5) -> 0.19695048 | J5: =MEDIAN(D5:G5) -> 0.14105518
B6: EBITDA Growth | D6: =(Assumptions!D9-Assumptions!C9)/ABS(Assumptions!C9) -> 1.5342312 | E6: =(Assumptions!E9-Assumptions!D9)/ABS(Assumptions!D9) -> -0.48184234 | F6: =(Assumptions!F9-Assumptions!E9)/ABS(Assumptions!E9) -> 0.19700855 | G6: =(Assumptions!G9-Assumptions!F9)/ABS(Assumptions!F9) -> 1.6804713 | I6: =AVERAGE(D6:G6) -> 0.73246717 | J6: =MEDIAN(D6:G6) -> 0.86561987
B7: EBIT Growth | D7: =(Assumptions!D11-Assumptions!C11)/ABS(Assumptions!C11) -> 2.1284014 | E7: =(Assumptions!E11-Assumptions!D11)/ABS(Assumptions!D11) -> -0.5585757 | F7: =(Assumptions!F11-Assumptions!E11)/ABS(Assumptions!E11) -> 0.26293103 | G7: =(Assumptions!G11-Assumptions!F11)/ABS(Assumptions!F11) -> 2.3057045 | I7: =AVERAGE(D7:G7) -> 1.0346153 | J7: =MEDIAN(D7:G7) -> 1.1956662
B8: Net Profit Growth | D8: =(Assumptions!D17-Assumptions!C17)/ABS(Assumptions!C17) -> 1.2761813 | E8: =(Assumptions!E17-Assumptions!D17)/ABS(Assumptions!D17) -> -0.51471927 | F8: =(Assumptions!F17-Assumptions!E17)/ABS(Assumptions!E17) -> 0.37569314 | G8: =(Assumptions!G17-Assumptions!F17)/ABS(Assumptions!F17) -> 1.6456338 | I8: =AVERAGE(D8:G8) -> 0.69569724 | J8: =MEDIAN(D8:G8) -> 0.8259372
B10: Margin Ratios
B11: EBITDA Margin | C11: =(Assumptions!C9/Assumptions!C3) -> 0.19897276 | D11: =(Assumptions!D9/Assumptions!D3) -> 0.31845427 | E11: =(Assumptions!E9/Assumptions!E3) -> 0.1641299 | F11: =(Assumptions!F9/Assumptions!F3) -> 0.21302 | G11: =(Assumptions!G9/Assumptions!G3) -> 0.44722421 | I11: =(AVERAGE(C11:G11)) -> 0.26836023 | J11: =(MEDIAN(C11:G11)) -> 0.21302
B12: EBIT Margin | C12: =(Assumptions!C11/Assumptions!C3) -> 0.13130862 | D12: =(Assumptions!D11/Assumptions!D3) -> 0.25943163 | E12: =(Assumptions!E11/Assumptions!E3) -> 0.11390896 | F12: =(Assumptions!F11/Assumptions!F3) -> 0.15598144 | G12: =(Assumptions!G11/Assumptions!G3) -> 0.4038599 | I12: =(AVERAGE(C12:G12)) -> 0.21289811 | J12: =(MEDIAN(C12:G12)) -> 0.15598144
B13: EBT Margin | C13: =(Assumptions!C14/Assumptions!C3) -> 0.1469406 | D13: =(Assumptions!D14/Assumptions!D3) -> 0.27882378 | E13: =(Assumptions!E14/Assumptions!E3) -> 0.12941011 | F13: =(Assumptions!F14/Assumptions!F3) -> 0.20625143 | G13: =(Assumptions!G14/Assumptions!G3) -> 0.42161067 | I13: =(AVERAGE(C13:G13)) -> 0.23660732 | J13: =(MEDIAN(C13:G13)) -> 0.20625143
B14: PAT Margin | C14: =(Assumptions!C17/Assumptions!C3) -> 0.14547119 | D14: =(Assumptions!D17/Assumptions!D3) -> 0.20911783 | E14: =(Assumptions!E17/Assumptions!E3) -> 0.10093989 | F14: =(Assumptions!F17/Assumptions!F3) -> 0.15056354 | G14: =(Assumptions!G17/Assumptions!G3) -> 0.3119919 | I14: =(AVERAGE(C14:G14)) -> 0.18361687 | J14: =(MEDIAN(C14:G14)) -> 0.15056354
B16: Return Ratios
B17: Pre-Tax ROIC | C17: =Assumptions!C39 -> 0.093847259 | D17: =Assumptions!D39 -> 0.22522192 | E17: =Assumptions!E39 -> 0.10580494 | F17: =Assumptions!F39 -> 0.12022979 | G17: =Assumptions!G39 -> 0.28957034 | I17: =(AVERAGE(C17:G17)) -> 0.16693485 | J17: =(MEDIAN(C17:G17)) -> 0.12022979
B18: Post-Tax ROIC | C18: =Assumptions!C40 -> 0.070385444 | D18: =Assumptions!D40 -> 0.16891644 | E18: =Assumptions!E40 -> 0.079353704 | F18: =Assumptions!F40 -> 0.090172343 | G18: =Assumptions!G40 -> 0.21717776 | I18: =(AVERAGE(C18:G18)) -> 0.12520114 | J18: =(MEDIAN(C18:G18)) -> 0.090172343
B20: Other Ratios
B21: Dividend Growth | D21: =('Consolidated FS'!E22*'Consolidated FS'!E30-'Consolidated FS'!D22*'Consolidated FS'!D30)/ABS('Consolidated FS'!D22*'Consolidated FS'!D30) -> 0.85448775 | E21: =('Consolidated FS'!F22*'Consolidated FS'!F30-'Consolidated FS'!E22*'Consolidated FS'!E30)/ABS('Consolidated FS'!E22*'Consolidated FS'!E30) -> -0.29490003 | F21: =('Consolidated FS'!G22*'Consolidated FS'!G30-'Consolidated FS'!F22*'Consolidated FS'!F30)/ABS('Consolidated FS'!F22*'Consolidated FS'!F30) -> 0.098738436 | G21: =('Consolidated FS'!H22*'Consolidated FS'!H30-'Consolidated FS'!G22*'Consolidated FS'!G30)/ABS('Consolidated FS'!G22*'Consolidated FS'!G30) -> 1.1314408 | I21: =(AVERAGE(D21:G21)) -> 0.44744174 | J21: =(MEDIAN(D21:G21)) -> 0.47661309
B22: EPS Growth | D22: =('Consolidated FS'!E29-'Consolidated FS'!D29)/ABS('Consolidated FS'!D29) -> 1.2729844 | E22: =('Consolidated FS'!F29-'Consolidated FS'!E29)/ABS('Consolidated FS'!E29) -> -0.51400124 | F22: =('Consolidated FS'!G29-'Consolidated FS'!F29)/ABS('Consolidated FS'!F29) -> 0.38668374 | G22: =('Consolidated FS'!H29-'Consolidated FS'!G29)/ABS('Consolidated FS'!G29) -> 1.6481994 | I22: =(AVERAGE(D22:G22)) -> 0.6984666 | J22: =(MEDIAN(D22:G22)) -> 0.82983409

Sheet Fixed Asset Schedule
B2: Particulars | C2: 2021 | D2: 2022 | E2: 2023 | F2: 2024 | G2: 2025
B3: Beginning Balance (Net Fixed Assets) | D3: =C7 -> 7660 | E3: =D7 -> 7343 | F3: =E7 -> 7303 | G3: =F7 -> 7383
B4: Add: Net Purchases (Capex) | D4: =D5-D3 -> 520 | E4: =E5-E3 -> 676 | F4: =F5-F3 -> 830 | G4: =G5-G3 -> 1093
B5: Total Fixed Assets (Gross) | D5: =D6+D7 -> 8180 | E5: =E6+E7 -> 8019 | F5: =F6+F7 -> 8133 | G5: =G6+G7 -> 8476
B6: Less: Depreciation & Amortisation | C6: ='Consolidated FS'!D19 -> 606 | D6: ='Consolidated FS'!E19 -> 837 | E6: ='Consolidated FS'!F19 -> 716 | F6: ='Consolidated FS'!G19 -> 750 | G6: ='Consolidated FS'!H19 -> 728
B7: Closing Balance (Net Fixed Assets) | C7: ='Consolidated FS'!R17 -> 7660 | D7: ='Consolidated FS'!S17 -> 7343 | E7: ='Consolidated FS'!T17 -> 7303 | F7: ='Consolidated FS'!U17 -> 7383 | G7: ='Consolidated FS'!V17 -> 7748
B9: Net Capital Expenditure | D9: =D4-D6 -> -317 | E9: =E4-E6 -> -40 | F9: =F4-F6 -> 80 | G9: =G4-G6 -> 365
B10: Net Capex / Sales (%) | D10: =D9/'Consolidated FS'!E4 -> -0.022353854 | E10: =E9/'Consolidated FS'!F4 -> -0.0028056393 | F10: =F9/'Consolidated FS'!G4 -> 0.0060841129 | G10: =G9/'Consolidated FS'!H4 -> 0.02174172
B12: Median Capital expenditure /Sales percentage | C12: =MEDIAN(D10:G10) -> 0.0016392368
B13: Average Capital expenditure /Sales percentage | C13: =AVERAGE(D10:G10) -> 0.00066658501

Sheet FCFF
B2: Particulars | C2: 2021 | D2: 2022 | E2: 2023 | F2: 2024 | G2: 2025
B3: EBIT | C3: =Assumptions!C11 -> 1176 | D3: =Assumptions!D11 -> 3679 | E3: =Assumptions!E11 -> 1624 | F3: =Assumptions!F11 -> 2051 | G3: =Assumptions!G11 -> 6780
B4: Less: Tax on EBIT (25%) | C4: =25%*C3 -> 294 | D4: =25%*D3 -> 919.75 | E4: =25%*E3 -> 406 | F4: =25%*F3 -> 512.75 | G4: =25%*G3 -> 1695
B5: NOPAT [EBIT × (1 − Tax)] | C5: =C3-C4 -> 882 | D5: =D3-D4 -> 2759.25 | E5: =E3-E4 -> 1218 | F5: =F3-F4 -> 1538.25 | G5: =G3-G4 -> 5085
B6: Less: Net Capital Expenditure | D6: ='Fixed Asset Schedule'!D9 -> -317 | E6: ='Fixed Asset Schedule'!E9 -> -40 | F6: ='Fixed Asset Schedule'!F9 -> 80 | G6: ='Fixed Asset Schedule'!G9 -> 365
B7: Less: Change in Working Capital | D7: ='Changes in WC'!D7 -> -419 | E7: ='Changes in WC'!E7 -> 404 | F7: ='Changes in WC'!F7 -> -180 | G7: ='Changes in WC'!G7 -> 869
B8: Reinvestment (Capex + ΔWCL) | C8: =SUM(C6:C7) -> 0 | D8: =SUM(D6:D7) -> -736 | E8: =SUM(E6:E7) -> 364 | F8: =SUM(F6:F7) -> -100 | G8: =SUM(G6:G7) -> 1234
B9: Free Cash Flow to Firm (FCFF) | C9: =C5-C8 -> 882 | D9: =D5-D8 -> 3495.25 | E9: =E5-E8 -> 854 | F9: =F5-F8 -> 1638.25 | G9: =G5-G8 -> 3851
B11: Reinvestment Rate | D11: =D8/D3 -> -0.20005436 | E11: =E8/E3 -> 0.22413793 | F11: =F8/F3 -> -0.048756704 | G11: =G8/G3 -> 0.1820059
B13: Median Reinvestment rate /Sales percentage | C13: =MEDIAN(D11:G11) -> 0.066624598
B14: Average Reinvestment rate /Sales percentage | C14: =AVERAGE(D11:G11) -> 0.039333191

Sheet Changes in WC
B2: Particulars | C2: 2021 | D2: 2022 | E2: 2023 | F2: 2024 | G2: 2025
B3: Inventories | C3: ='Consolidated FS'!R32 -> 1476 | D3: ='Consolidated FS'!S32 -> 1646 | E3: ='Consolidated FS'!T32 -> 1840 | F3: ='Consolidated FS'!U32 -> 1830 | G3: ='Consolidated FS'!V32 -> 1909
B4: Trade Receivables | C4: ='Consolidated FS'!R33 -> 147 | D4: ='Consolidated FS'!S33 -> 75 | E4: ='Consolidated FS'!T33 -> 91 | F4: ='Consolidated FS'!U33 -> 154 | G4: ='Consolidated FS'!V33 -> 186
B5: Trade Payables | C5: ='Consolidated FS'!R13 -> 940 | D5: ='Consolidated FS'!S13 -> 1457 | E5: ='Consolidated FS'!T13 -> 1263 | F5: ='Consolidated FS'!U13 -> 1496 | G5: ='Consolidated FS'!V13 -> 738
B6: Non-Cash Working Capital | C6: =C3+C4-C5 -> 683 | D6: =D3+D4-D5 -> 264 | E6: =E3+E4-E5 -> 668 | F6: =F3+F4-F5 -> 488 | G6: =G3+G4-G5 -> 1357
B7: Change in Working Capital | D7: =D6-C6 -> -419 | E7: =E6-D6 -> 404 | F7: =F6-E6 -> -180 | G7: =G6-F6 -> 869
B8: Change in WC / Sales (%) | D8: =D7/'Consolidated FS'!E4 -> -0.029546576 | E8: =E7/'Consolidated FS'!F4 -> 0.028336957 | F8: =F7/'Consolidated FS'!G4 -> -0.013689254 | G8: =G7/'Consolidated FS'!H4 -> 0.051763164
B10: Median Non-Cash WC / Sales (%) | C10: =MEDIAN(D8:G8) -> 0.0073238517
B11: Average Change in working capital / % of sales | C11: =AVERAGE(D8:G8) -> 0.0092160728

Sheet WACC
B2: National Aluminium Corporation. — Weighted Average Cost of Capital (WACC)
B4: Capital Structure (FY2025 Balance Sheet — Market Value Weights)
B5: Particulars | C5: Book Value (₹ Cr) | D5: Market Value (₹ Cr) | E5: Weight
B6: Equity (Market Cap) | C6: =Assumptions!G34 -> 17805 | D6: ='Raw FS Valuation'!F3 -> 220677.65 | E6: =D6/D8 -> 0.99917595
B7: Debt (Book Value of Borrowings) | C7: =Assumptions!G35 -> 182 | D7: =C7 -> 182 | E7: =D7/D8 -> 0.00082405274
B8: Total Capital | C8: =SUM(C6:C7) -> 17987 | D8: =SUM(D6:D7) -> 220859.65
B10: Cost of Equity (Capital Asset Pricing Model — CAPM)
B11: Particulars | C11: Value
B12: Risk-Free Rate (Rf) | C12: 0.06
B13: Equity Risk Premium (ERP) | C13: 0.0744
B14: Beta Regressed (5-yr daily vs Nifty 50) | C14: =Beta!K5 -> 1.3379164
B15: Debt/Equity ratio (D/E) | C15: =D7/D6 -> 0.00082473236
B16: Beta × ERP | C16: =C14*C13 -> 0.099540978
B17: Cost of Equity [Ke = Rf + Beta × ERP] | C17: =C12+C16 -> 0.15954098
B19: Cost of Debt (Post-Tax)
B20: Particulars | C20: Value
B21: Total Interest Expense (FY2025) | C21: =Assumptions!G13 -> 59
B22: Average Total Borrowings (FY2024-FY2025) | C22: =AVERAGE(Assumptions!F35,Assumptions!G35) -> 139
B23: Pre-Tax Cost of Debt [Kd = Interest / Avg Debt] | C23: =C21/C22 -> 0.42446043
B24: Marginal Tax Rate | C24: =Assumptions!G30 -> 0.25
B25: Post-Tax Cost of Debt [Kd(1-t)] | C25: =C23*(1-C24) -> 0.31834532
B27: WACC Calculation [WACC = Ke × We + Kd(1-t) × Wd]
B28: Component | C28: Cost (%) | D28: Weight (%) | E28: Contribution (%)
B29: Equity | C29: =C17 -> 0.15954098 | D29: =E6 -> 0.99917595 | E29: =C29*D29 -> 0.15940951
B30: Debt | C30: =C25 -> 0.31834532 | D30: =E7 -> 0.00082405274 | E30: =C30*D30 -> 0.00026233334
B31: WACC | E31: =SUM(E29:E30) -> 0.15967184

Sheet Raw FS Valuation
B2: Sno. | C2: Name | D2: CMP Rs. | E2: P/E | F2: Mar Cap Rs.Cr. | G2: Div Yld % | H2: NP Qtr Rs.Cr. | I2: Qtr Profit Var % | J2: ROCE % | K2: Debt Rs.Cr. | L2: EV / EBITDA | M2: No. Eq. Shares Cr. | N2: EBIT 12M Rs.Cr. | O2: NP Ann Rs.Cr. | P2: Sales Rs.Cr. | Q2: Cash End Rs.Cr.
B3: 1 | C3: Hindalco Inds. | D3: 982 | E3: 12.6 | F3: 220677.65 | G3: 0.5 | H3: 2597 | I3: -22.12 | J3: 13.67 | K3: 99161 | L3: 8.08 | M3: 224.72 | N3: 28939 | O3: 13391 | P3: 274944 | Q3: 14808
B4: 2 | C4: Natl. Aluminium | D4: 351.6 | E4: 11.09 | F4: 64575.99 | G4: 2.89 | H4: 1722.44 | I4: -16.68 | J4: 39.59 | K4: 59.83 | L4: 6.54 | M4: 183.66 | N4: 7848.5 | O4: 5797.01 | P4: 17843.05 | Q4: 8407.74
B5: 3 | C5: Arfin India | D5: 96.14 | E5: 119.24 | F5: 1622.12 | G5: 0.11 | H5: 5.71 | I5: 957.41 | J5: 13.97 | K5: 129.27 | L5: 39.1 | M5: 16.87 | N5: 39.92 | O5: 13.6 | P5: 624.9 | Q5: 8.86
B6: 4 | C6: Maan Aluminium | D6: 127 | E6: 58.44 | F6: 761.8 | G6: 0 | H6: 1.7 | I6: -56.85 | J6: 7.73 | K6: 54.79 | L6: 25.43 | M6: 6 | N6: 23.12 | O6: 13.03 | P6: 808.71 | Q6: 38.44
B7: 5 | C7: MMP Industries | D7: 274.45 | E7: 18.07 | F7: 697.18 | G7: 0.7 | H7: 17.99 | I7: 14.36 | J7: 12.49 | K7: 184.53 | L7: 11.81 | M7: 2.54 | N7: 63.13 | O7: 31.01 | P7: 824 | Q7: 2.01
B8: 6 | C8: Msafe Equipments | D8: 208 | E8: 18.95 | F8: 424.31 | G8: 0 | H8: 11.92 | I8: 91.95 | J8: 34.11 | K8: 38.59 | L8: 10.13 | M8: 2.04 | N8: 33.22 | O8: 22.42 | P8: 103.5 | Q8: 43.18
C9: Median: 10 Co. | D9: 204.4 | E9: 18.51 | F9: 729.49 | G9: 0.06 | H9: 7.85 | I9: 14.36 | J9: 13.67 | K9: 94.55 | L9: 9.98 | M9: 6.28 | N9: 35.84 | O9: 13.81 | P9: 594.4 | Q9: 13.49

Sheet Relative Valuation
B2: Relative Valuation - National Aluminium Company Ltd
B3: Figures in Crore
B4: Comparable Company Valuation
B5: Company Name | C5: Market Data | J5: Financials | O5: Valuation
C6: No. of shares | D6: Share Price | E6: Equity value | F6: Debt | G6: cash | H6: Enterprises value | J6: Revenue | K6: EBITDA | L6: Net Profit | M6: EPS | O6: EV/Revenue | P6: EV/EBITDA | Q6: P/E Ratio
B7: Hindalco Inds. | C7: ='Raw FS Valuation'!M3 -> 224.72 | D7: ='Raw FS Valuation'!D3 -> 982 | E7: =C7*D7 -> 220675.04 | F7: ='Raw FS Valuation'!K3 -> 99161 | G7: ='Raw FS Valuation'!Q3 -> 14808 | H7: =E7+F7-G7 -> 305028.04 | J7: ='Raw FS Valuation'!P3 -> 274944 | K7: =H7/'Raw FS Valuation'!L3 -> 37750.995 | L7: ='Raw FS Valuation'!O3 -> 13391 | M7: =L7/C7 -> 59.589712 | O7: =H7/J7 -> 1.1094188 | P7: =H7/K7 -> 8.08 | Q7: =D7/M7 -> 16.479355
B8: Natl. Aluminium | C8: ='Raw FS Valuation'!M4 -> 183.66 | D8: ='Raw FS Valuation'!D4 -> 351.6 | E8: =C8*D8 -> 64574.856 | F8: ='Raw FS Valuation'!K4 -> 59.83 | G8: ='Raw FS Valuation'!Q4 -> 8407.74 | H8: =E8+F8-G8 -> 56226.946 | J8: ='Raw FS Valuation'!P4 -> 17843.05 | K8: =H8/'Raw FS Valuation'!L4 -> 8597.3924 | L8: ='Raw FS Valuation'!O4 -> 5797.01 | M8: =L8/C8 -> 31.563814 | O8: =H8/J8 -> 3.1511959 | P8: =H8/K8 -> 6.54 | Q8: =D8/M8 -> 11.139338
B9: Arfin India | C9: ='Raw FS Valuation'!M5 -> 16.87 | D9: ='Raw FS Valuation'!D5 -> 96.14 | E9: =C9*D9 -> 1621.8818 | F9: ='Raw FS Valuation'!K5 -> 129.27 | G9: ='Raw FS Valuation'!Q5 -> 8.86 | H9: =E9+F9-G9 -> 1742.2918 | J9: ='Raw FS Valuation'!P5 -> 624.9 | K9: =H9/'Raw FS Valuation'!L5 -> 44.559893 | L9: ='Raw FS Valuation'!O5 -> 13.6 | M9: =L9/C9 -> 0.80616479 | O9: =H9/J9 -> 2.788113 | P9: =H9/K9 -> 39.1 | Q9: =D9/M9 -> 119.25601
B10: Maan Aluminium | C10: ='Raw FS Valuation'!M6 -> 6 | D10: ='Raw FS Valuation'!D6 -> 127 | E10: =C10*D10 -> 762 | F10: ='Raw FS Valuation'!K6 -> 54.79 | G10: ='Raw FS Valuation'!Q6 -> 38.44 | H10: =E10+F10-G10 -> 778.35 | J10: ='Raw FS Valuation'!P6 -> 808.71 | K10: =H10/'Raw FS Valuation'!L6 -> 30.60755 | L10: ='Raw FS Valuation'!O6 -> 13.03 | M10: =L10/C10 -> 2.1716667 | O10: =H10/J10 -> 0.96245873 | P10: =H10/K10 -> 25.43 | Q10: =D10/M10 -> 58.48043
B11: MMP Industries | C11: ='Raw FS Valuation'!M7 -> 2.54 | D11: ='Raw FS Valuation'!D7 -> 274.45 | E11: =C11*D11 -> 697.103 | F11: ='Raw FS Valuation'!K7 -> 184.53 | G11: ='Raw FS Valuation'!Q7 -> 2.01 | H11: =E11+F11-G11 -> 879.623 | J11: ='Raw FS Valuation'!P7 -> 824 | K11: =H11/'Raw FS Valuation'!L7 -> 74.481202 | L11: ='Raw FS Valuation'!O7 -> 31.01 | M11: =L11/C11 -> 12.208661 | O11: =H11/J11 -> 1.0675036 | P11: =H11/K11 -> 11.81 | Q11: =D11/M11 -> 22.479942
B12: Msafe Equipments | C12: ='Raw FS Valuation'!M8 -> 2.04 | D12: ='Raw FS Valuation'!D8 -> 208 | E12: =C12*D12 -> 424.32 | F12: ='Raw FS Valuation'!K8 -> 38.59 | G12: ='Raw FS Valuation'!Q8 -> 43.18 | H12: =E12+F12-G12 -> 419.73 | J12: ='Raw FS Valuation'!P8 -> 103.5 | K12: =H12/'Raw FS Valuation'!L8 -> 41.434353 | L12: ='Raw FS Valuation'!O8 -> 22.42 | M12: =L12/C12 -> 10.990196 | O12: =H12/J12 -> 4.0553623 | P12: =H12/K12 -> 10.13 | Q12: =D12/M12 -> 18.925959
B15: Particulars | D15: EV/Revenue | E15: EV/EBITDA | F15: P/E Ratio
B16: Implied Enterprise Value | D16: =J7*O18 -> 601854.82 | E16: =K7*P19 -> 414128.42 | F16: =L7*Q19 -> 277233.21 | M16: Max | O16: =MAX(O7:O12) -> 4.0553623 | P16: =MAX(P7:P12) -> 39.1 | Q16: =MAX(Q7:Q12) -> 119.25601
B17: Net Debt | D17: =F7-G7 -> 84353 | E17: =D17 -> 84353 | F17: 0 | M17: 75th Percentile | O17: =QUARTILE(O7:O12,3) -> 3.0604252 | P17: =QUARTILE(P7:P12,3) -> 22.025 | Q17: =QUARTILE(Q7:Q12,3) -> 49.480308
B18: Implied Market Value | D18: =D16-D17 -> 517501.82 | E18: =E16-E17 -> 329775.42 | F18: =F16-F17 -> 277233.21 | M18: Average | O18: =AVERAGE(O7:O12) -> 2.1890087 | P18: =AVERAGE(P7:P12) -> 16.848333 | Q18: =AVERAGE(Q7:Q12) -> 41.12684
B19: Share Outstanding | D19: =C7 -> 224.72 | E19: =D19 -> 224.72 | F19: =E19 -> 224.72 | M19: Median | O19: =MEDIAN(O7:O12) -> 1.9487659 | P19: =MEDIAN(P7:P12) -> 10.97 | Q19: =MEDIAN(Q7:Q12) -> 20.70295
B20: Implied Value per Share | D20: =D18/D19 -> 2302.8739 | E20: =E18/E19 -> 1467.4947 | F20: =F18/F19 -> 1233.6828 | M20: 25th Percentile | O20: =QUARTILE(O7:O12,1) -> 1.0779824 | P20: =QUARTILE(P7:P12,1) -> 8.5925 | Q20: =QUARTILE(Q7:Q12,1) -> 17.091006
M21: Min. | O21: =MIN(O7:O12) -> 0.96245873 | P21: =MIN(P7:P12) -> 6.54 | Q21: =MIN(Q7:Q12) -> 11.139338

Sheet Growth scenerio
B2: National Aluminium Company Ltd - "Growth Scenarios"
B4: Scenario 1: High Growth | O4: Average Of Revenue Growth | P4: =MEDIAN(Assumptions!D4:G4) -> 0.14105518
B5: INR Cr. | C5: LTM | D5: Y1E | E5: Y2E | F5: Y3E | G5: Y4W | H5: Y5E | I5: Y6E | J5: Y7E | K5: Y8E | L5: Y9E | M5: Y10E | O5: Risk free rate | P5: 0.067
B6: Sales | C6: =Assumptions!G3 -> 16788 | D6: =C6*(1+D7) -> 19156.034 | E6: =D6*(1+E7) -> 21700.47 | F6: =E6*(1+F7) -> 24404.315 | G6: =F6*(1+G7) -> 27244.248 | H6: =G6*(1+H7) -> 30190.49 | I6: =H6*(1+I7) -> 33206.924 | J6: =I6*(1+J7) -> 36251.503 | K6: =J6*(1+K7) -> 39276.934 | ... M6: =L6*(1+M7) -> 45061.196 | P6: =P4-P5 -> 0.074055184
B7: Sales Growth % | D7: =P4 -> 0.14105518 | E7: =D7-$P$7 -> 0.13282683 | F7: =E7-$P$7 -> 0.12459848 | G7: =F7-$P$7 -> 0.11637012 | H7: =G7-$P$7 -> 0.10814177 | I7: =H7-$P$7 -> 0.099913415 | J7: =I7-$P$7 -> 0.091685061 | K7: =J7-$P$7 -> 0.083456707 | L7: =K7-$P$7 -> 0.075228354 | M7: =L7-$P$7 -> 0.067 | O7: Per Year | P7: =P6/9 -> 0.0082283537
O8: =P6/9 -> 0.0082283537
B10: Scenario 2: Average Growth | O10: Average Growth | P10: =Assumptions!C20 -> 0.19695048
B11: INR Cr. | C11: LTM | D11: Y1E | E11: Y2E | F11: Y3E | G11: Y4W | H11: Y5E | I11: Y6E | J11: Y7E | K11: Y8E | L11: Y9E | M11: Y10E | O11: Risk free rate | P11: 0.067
B12: Sales | C12: =C6 -> 16788 | D12: =C12*(1+D13) -> 20094.405 | E12: =D12*(1+E13) -> 23761.865 | F12: =E12*(1+F13) -> 27755.584 | G12: =F12*(1+G13) -> 32019.776 | H12: =G12*(1+H13) -> 36476.759 | I12: =H12*(1+I13) -> 41027.445 | J12: =I12*(1+J13) -> 45553.463 | K12: =J12*(1+K13) -> 49921.033 | ... M12: =L12*(1+M13) -> 57603.647 | P12: =P10-P11 -> 0.12995048
B13: Sales Growth % | D13: =Assumptions!C20 -> 0.19695048 | E13: =D13-$P$13 -> 0.18251154 | F13: =E13-$P$13 -> 0.1680726 | G13: =F13-$P$13 -> 0.15363365 | H13: =G13-$P$13 -> 0.13919471 | I13: =H13-$P$13 -> 0.12475577 | J13: =I13-$P$13 -> 0.11031683 | K13: =J13-$P$13 -> 0.095877885 | L13: =K13-$P$13 -> 0.081438942 | M13: =L13-$P$13 -> 0.067 | O13: Per Year | P13: =P12/9 -> 0.014438942
O14: =P12/9 -> 0.014438942
B16: Scenario 3: EBIT Growth | O16: Growth in EBIT | P16: =Assumptions!C46 -> 0.014469381
B17: INR Cr. | C17: LTM | D17: Y1E | E17: Y2E | F17: Y3E | G17: Y4W | H17: Y5E | I17: Y6E | J17: Y7E | K17: Y8E | L17: Y9E | M17: Y10E | O17: Risk free rate | P17: 0.067
B18: Sales | C18: =C12 -> 16788 | D18: =C18*(1+D19) -> 17030.912 | E18: =D18*(1+E19) -> 17376.744 | F18: =E18*(1+F19) -> 17831.021 | G18: =F18*(1+G19) -> 18401.25 | H18: =G18*(1+H19) -> 19097.118 | I18: =H18*(1+I19) -> 19930.765 | J18: =I18*(1+J19) -> 20917.135 | K18: =J18*(1+K19) -> 22074.407 | ... M18: =L18*(1+M19) -> 24993.995 | P18: =P16-P17 -> -0.052530619
B19: Sales Growth % | D19: =Assumptions!C46 -> 0.014469381 | E19: =D19-$P$19 -> 0.020306116 | F19: =E19-$P$19 -> 0.026142852 | G19: =F19-$P$19 -> 0.031979587 | H19: =G19-$P$19 -> 0.037816323 | I19: =H19-$P$19 -> 0.043653058 | J19: =I19-$P$19 -> 0.049489794 | K19: =J19-$P$19 -> 0.055326529 | L19: =K19-$P$19 -> 0.061163265 | M19: =L19-$P$19 -> 0.067 | O19: Per Year | P19: =P18/9 -> -0.0058367355
O20: =P18/9 -> -0.0058367355
B21: Live Scenario | C21: 3
B22: INR Cr. | C22: LTM | D22: Y1E | E22: Y2E | F22: Y3E | G22: Y4W | H22: Y5E | I22: Y6E | J22: Y7E | K22: Y8E | L22: Y9E | M22: Y10E
B23: Sales | C23: =C6 -> 16788 | D23: =C23*(1+D24) -> 17030.912 | E23: =D23*(1+E24) -> 17376.744 | F23: =E23*(1+F24) -> 17831.021 | G23: =F23*(1+G24) -> 18401.25 | H23: =G23*(1+H24) -> 19097.118 | I23: =H23*(1+I24) -> 19930.765 | J23: =I23*(1+J24) -> 20917.135 | K23: =J23*(1+K24) -> 22074.407 | ... M23: =L23*(1+M24) -> 24993.995
B24: Sales Growth % | D24: =CHOOSE($C$21,D7,D13,D19) -> 0.014469381 | E24: =CHOOSE($C$21,E7,E13,E19) -> 0.020306116 | F24: =CHOOSE($C$21,F7,F13,F19) -> 0.026142852 | G24: =CHOOSE($C$21,G7,G13,G19) -> 0.031979587 | H24: =CHOOSE($C$21,H7,H13,H19) -> 0.037816323 | I24: =CHOOSE($C$21,I7,I13,I19) -> 0.043653058 | J24: =CHOOSE($C$21,J7,J13,J19) -> 0.049489794 | K24: =CHOOSE($C$21,K7,K13,K19) -> 0.055326529 | ... M24: =CHOOSE($C$21,M7,M13,M19) -> 0.067

Sheet DCF
B1: National Aluminium Company Ltd - "VALUATION"
D2: 1 | E2: 2 | F2: 3 | G2: 4 | H2: 5 | I2: 6 | J2: 7 | K2: 8 | L2: 9 | M2: 10
B3: INR Cr | C3: LTM | D3: Y1E | E3: Y2E | F3: Y3E | G3: Y4W | H3: Y5E | I3: Y6E | J3: Y7E | K3: Y8E | L3: Y9E | M3: Y10E | N3: Terminal Yr | P3: Terminal growth rate % | Q3: 0.05
B4: Sales | C4: ='Growth scenerio'!C23 -> 16788 | D4: ='Growth scenerio'!D23 -> 17030.912 | E4: ='Growth scenerio'!E23 -> 17376.744 | F4: ='Growth scenerio'!F23 -> 17831.021 | G4: ='Growth scenerio'!G23 -> 18401.25 | H4: ='Growth scenerio'!H23 -> 19097.118 | I4: ='Growth scenerio'!I23 -> 19930.765 | J4: ='Growth scenerio'!J23 -> 20917.135 | ... M4: ='Growth scenerio'!M23 -> 24993.995 | N4: =M4*(1+Q3) -> 26243.694 | P4: Cost of Capital % | Q4: =WACC!E31 -> 0.15967184
B5: Sales Growth | D5: ='Growth scenerio'!D24 -> 0.014469381 | E5: ='Growth scenerio'!E24 -> 0.020306116 | F5: ='Growth scenerio'!F24 -> 0.026142852 | G5: ='Growth scenerio'!G24 -> 0.031979587 | H5: ='Growth scenerio'!H24 -> 0.037816323 | I5: ='Growth scenerio'!I24 -> 0.043653058 | J5: ='Growth scenerio'!J24 -> 0.049489794 | K5: ='Growth scenerio'!K24 -> 0.055326529 | ... M5: ='Growth scenerio'!M24 -> 0.067 | N5: =Q3 -> 0.05 | P5: Terminal reinvestment rate % | Q5: =Q3/AVERAGE(Assumptions!$C$40:$G$40) -> 0.3993574
B6: EBIT | D6: =D7*D4 -> 6878.1024 | E6: =E7*E4 -> 7017.7699 | F6: =F7*F4 -> 7201.2345 | G6: =G7*G4 -> 7431.527 | H6: =H7*H4 -> 7712.56 | I6: =I7*I4 -> 8049.2368 | J6: =J7*J4 -> 8447.5919 | K6: =K7*K4 -> 8914.9678 | ... N6: =N7*N4 -> 10598.776
B7: EBIT Margin % | D7: =Assumptions!$G$24 -> 0.4038599 | E7: =Assumptions!$G$24 -> 0.4038599 | F7: =Assumptions!$G$24 -> 0.4038599 | G7: =Assumptions!$G$24 -> 0.4038599 | H7: =Assumptions!$G$24 -> 0.4038599 | I7: =Assumptions!$G$24 -> 0.4038599 | J7: =Assumptions!$G$24 -> 0.4038599 | K7: =Assumptions!$G$24 -> 0.4038599 | ... M7: =Assumptions!$G$24 -> 0.4038599 | N7: =M7 -> 0.4038599
B8: Less: Tax on EBIT | D8: =Assumptions!$C$30*D6 -> 1719.5256 | E8: =Assumptions!$C$30*E6 -> 1754.4425 | F8: =Assumptions!$C$30*F6 -> 1800.3086 | G8: =Assumptions!$C$30*G6 -> 1857.8817 | H8: =Assumptions!$C$30*H6 -> 1928.14 | I8: =Assumptions!$C$30*I6 -> 2012.3092 | J8: =Assumptions!$C$30*J6 -> 2111.898 | K8: =Assumptions!$C$30*K6 -> 2228.742 | ... M8: =Assumptions!$C$30*M6 -> 2523.5181 | N8: =25%*N6 -> 2649.694
B9: EBIT(1-T) | D9: =D6-D8 -> 5158.5768 | E9: =E6-E8 -> 5263.3275 | F9: =F6-F8 -> 5400.9258 | G9: =G6-G8 -> 5573.6452 | H9: =H6-H8 -> 5784.42 | I9: =I6-I8 -> 6036.9276 | J9: =J6-J8 -> 6335.6939 | K9: =K6-K8 -> 6686.2259 | ... N9: =N6-N8 -> 7949.0819
B10: Less: Net Capital Expenditure | D10: ='Fixed Asset Schedule'!$C$12*D4 -> 27.917697 | E10: ='Fixed Asset Schedule'!$C$12*E4 -> 28.484597 | F10: ='Fixed Asset Schedule'!$C$12*F4 -> 29.229266 | G10: ='Fixed Asset Schedule'!$C$12*G4 -> 30.164005 | H10: ='Fixed Asset Schedule'!$C$12*H4 -> 31.304697 | I10: ='Fixed Asset Schedule'!$C$12*I4 -> 32.671243 | J10: ='Fixed Asset Schedule'!$C$12*J4 -> 34.288136 | K10: ='Fixed Asset Schedule'!$C$12*K4 -> 36.18518 | ... M10: ='Fixed Asset Schedule'!$C$12*M4 -> 40.971075
B11: Non Cash Working Capital | C11: ='Changes in WC'!G6 -> 1357 | D11: ='Changes in WC'!$C$10*DCF!D4 -> 124.73187 | E11: ='Changes in WC'!$C$10*DCF!E4 -> 127.26469 | F11: ='Changes in WC'!$C$10*DCF!F4 -> 130.59175 | G11: ='Changes in WC'!$C$10*DCF!G4 -> 134.76803 | H11: ='Changes in WC'!$C$10*DCF!H4 -> 139.86446 | I11: ='Changes in WC'!$C$10*DCF!I4 -> 145.96997 | J11: ='Changes in WC'!$C$10*DCF!J4 -> 153.19399 | K11: ='Changes in WC'!$C$10*DCF!K4 -> 161.66968 | ... M11: ='Changes in WC'!$C$10*DCF!M4 -> 183.05231
B12: Less: Change in Working Capital | D12: =D11-C11 -> -1232.2681 | E12: =E11-D11 -> 2.5328199 | F12: =F11-E11 -> 3.327062 | G12: =G11-F11 -> 4.1762704 | H12: =H11-G11 -> 5.0964311 | I12: =I11-H11 -> 6.1055112 | J12: =J11-I11 -> 7.2240236 | K12: =K11-J11 -> 8.4756918 | ... M12: =M11-L11 -> 11.494381
B13: Reinvestment | D13: =D10+D12 -> -1204.3504 | E13: =E10+E12 -> 31.017417 | F13: =F10+F12 -> 32.556328 | G13: =G10+G12 -> 34.340276 | H13: =H10+H12 -> 36.401128 | I13: =I10+I12 -> 38.776754 | J13: =J10+J12 -> 41.51216 | K13: =K10+K12 -> 44.660871 | ... M13: =M10+M12 -> 52.465456 | N13: =N9*N15 -> 3174.5246
B14: Free Cash Flow To Firm (FCFF) | D14: =D9-D13 -> 6362.9272 | E14: =E9-E13 -> 5232.31 | F14: =F9-F13 -> 5368.3695 | G14: =G9-G13 -> 5539.305 | H14: =H9-H13 -> 5748.0189 | I14: =I9-I13 -> 5998.1509 | J14: =J9-J13 -> 6294.1818 | K14: =K9-K13 -> 6641.565 | ... N14: =N9-N13 -> 4774.5572
B15: Implied Reinvestment rate % | D15: =D13/D9 -> -0.23346564 | E15: =E13/E9 -> 0.0058931193 | F15: =F13/F9 -> 0.006027916 | G15: =G13/G9 -> 0.006161188 | H15: =H13/H9 -> 0.0062929608 | I15: =I13/I9 -> 0.0064232598 | J15: =J13/J9 -> 0.0065521094 | K15: =K13/K9 -> 0.0066795338 | ... M15: =M13/M9 -> 0.0069302002 | N15: =Q5 -> 0.3993574
B17: Terminal Value | D17: =N14/(Q4-Q3) -> 43534.942
B19: Present Value Interest Factor(PVIF) | D19: =1/(1+$Q$4)^D2 -> 0.86231291 | E19: =1/(1+$Q$4)^E2 -> 0.74358355 | F19: =1/(1+$Q$4)^F2 -> 0.6412017 | G19: =1/(1+$Q$4)^G2 -> 0.5529165 | H19: =1/(1+$Q$4)^H2 -> 0.47678704 | I19: =1/(1+$Q$4)^I2 -> 0.41113962 | J19: =1/(1+$Q$4)^J2 -> 0.354531 | K19: =1/(1+$Q$4)^K2 -> 0.30571666 | ... M19: =1/(1+$Q$4)^M2 -> 0.22732588
B21: Present value of FCFF | D21: =SUMPRODUCT(D14:M14,D19:M19) -> 28917.834
B22: Present value of Terminal value | D22: =D17*M19 -> 9896.619
B24: Value of operating assets | D24: =D21+D22 -> 38814.453
B25: Add: Cash | D25: ='Consolidated FS'!V37 -> 5427
B26: Less: Debt | D26: ='Consolidated FS'!V6 -> 182
B27: Less: Minority Interest | D27: 0
B28: Equity Value | D28: =D24+D25-D26-D27 -> 44059.453
B30: No. of Shares outstanding (Cr) | D30: ='Raw FS Valuation'!M4 -> 183.66
B31: intrinsic value per share | D31: =D28/D30 -> 239.89684 | F31: Current 361
